{
  "AAPL": {
    "symbol": "AAPL",
    "name": "Apple Inc.",
    "closing_price": 188.01,
    "volume_weighted": 188.4191,
    "open_price": 187.845,
    "high_price": 189.5,
    "low_price": 187.78,
    "timestamp": 1700024400000,
    "num_trades": 564159
  },
  "MSFT": {
    "symbol": "MSFT",
    "name": "Microsoft Corporation",
    "closing_price": 369.67,
    "volume_weighted": 369.819,
    "open_price": 371.28,
    "high_price": 373.13,
    "low_price": 367.11,
    "timestamp": 1700024400000,
    "num_trades": 399873
  },
  "AAME": {
    "symbol": "AAME",
    "name": "Amazon.com Inc.",
    "closing_price": 1.85,
    "volume_weighted": 1.8043,
    "open_price": 1.83,
    "high_price": 1.87,
    "low_price": 1.75,
    "timestamp": 1700024400000,
    "num_trades": 47
  },
  "GOOGL": {
    "symbol": "GOOGL",
    "name": "Atlantic American Corp",
    "closing_price": 134.62,
    "volume_weighted": 134.3673,
    "open_price": 134.87,
    "high_price": 135.03,
    "low_price": 133.57,
    "timestamp": 1700024400000,
    "num_trades": 247415
  },
  "TSLA": {
    "symbol": "TSLA",
    "name": "Tesla Inc.",
    "closing_price": 242.84,
    "volume_weighted": 242.712,
    "open_price": 239.29,
    "high_price": 246.7,
    "low_price": 236.45,
    "timestamp": 1700024400000,
    "num_trades": 1552666
  },
  "META": {
    "symbol": "META",
    "name": "Meta Platforms Inc",
    "closing_price": 332.71,
    "volume_weighted": 333.8064,
    "open_price": 337.93,
    "high_price": 338.4,
    "low_price": 330.02,
    "timestamp": 1700024400000,
    "num_trades": 244791
  },
  "V": {
    "symbol": "V",
    "name": "Visa Inc.",
    "closing_price": 248.11,
    "volume_weighted": 247.8486,
    "open_price": 246.81,
    "high_price": 248.24,
    "low_price": 245.34,
    "timestamp": 1700024400000,
    "num_trades": 110035
  },
  "JPM": {
    "symbol": "JPM",
    "name": "JPMorgan Chase & Co.",
    "closing_price": 149.74,
    "volume_weighted": 149.6165,
    "open_price": 148.46,
    "high_price": 150.16,
    "low_price": 148.46,
    "timestamp": 1700024400000,
    "num_trades": 119818
  },
  "JNJ": {
    "symbol": "JNJ",
    "name": "Johnson & Johnson",
    "closing_price": 148.8,
    "volume_weighted": 148.6891,
    "open_price": 147.35,
    "high_price": 149.42,
    "low_price": 147.27,
    "timestamp": 1700024400000,
    "num_trades": 96163
  },
  "NVDA": {
    "symbol": "NVDA",
    "name": "NVIDIA Corporation",
    "closing_price": 488.88,
    "volume_weighted": 490.0315,
    "open_price": 499.35,
    "high_price": 499.6,
    "low_price": 482,
    "timestamp": 1700024400000,
    "num_trades": 700223
  },
  "PYPL": {
    "symbol": "PYPL",
    "name": "PayPal Holdings, Inc.",
    "closing_price": 58.25,
    "volume_weighted": 58.0287,
    "open_price": 57.0023,
    "high_price": 58.555,
    "low_price": 56.99,
    "timestamp": 1700024400000,
    "num_trades": 136611
  },
  "DIS": {
    "symbol": "DIS",
    "name": "Walt Disney Co (The)",
    "closing_price": 93.93,
    "volume_weighted": 93.8673,
    "open_price": 92.99,
    "high_price": 94.565,
    "low_price": 92.74,
    "timestamp": 1700024400000,
    "num_trades": 193483
  },
  "BABA": {
    "symbol": "BABA",
    "name": "Alibaba Group Holding Ltd",
    "closing_price": 87.07,
    "volume_weighted": 86.9548,
    "open_price": 86.96,
    "high_price": 87.83,
    "low_price": 85.89,
    "timestamp": 1700024400000,
    "num_trades": 266961
  },
  "PFE": {
    "symbol": "PFE",
    "name": "Pfizer Inc",
    "closing_price": 30.19,
    "volume_weighted": 30.0702,
    "open_price": 29.21,
    "high_price": 30.35,
    "low_price": 29.21,
    "timestamp": 1700024400000,
    "num_trades": 172426
  },
  "INTC": {
    "symbol": "INTC",
    "name": "Intel Corp",
    "closing_price": 40.61,
    "volume_weighted": 40.4288,
    "open_price": 39.585,
    "high_price": 40.84,
    "low_price": 39.58,
    "timestamp": 1700024400000,
    "num_trades": 247919
  },
  "CSCO": {
    "symbol": "CSCO",
    "name": "Cisco Systems Inc.",
    "closing_price": 53.28,
    "volume_weighted": 52.0116,
    "open_price": 53.27,
    "high_price": 53.43,
    "low_price": 53.035,
    "timestamp": 1700024400000,
    "num_trades": 201253
  },
  "VZ": {
    "symbol": "VZ",
    "name": "Verizon Communications Inc",
    "closing_price": 36,
    "volume_weighted": 35.9797,
    "open_price": 35.88,
    "high_price": 36.11,
    "low_price": 35.84,
    "timestamp": 1700024400000,
    "num_trades": 111040
  },
  "HD": {
    "symbol": "HD",
    "name": "The Home Depot, Inc.",
    "closing_price": 308.19,
    "volume_weighted": 307.4003,
    "open_price": 304.1,
    "high_price": 308.93,
    "low_price": 304.01,
    "timestamp": 1700024400000,
    "num_trades": 82843
  },
  "NFLX": {
    "symbol": "NFLX",
    "name": "Netflix Inc.",
    "closing_price": 461.94,
    "volume_weighted": 460.0683,
    "open_price": 452.81,
    "high_price": 462.7499,
    "low_price": 452.45,
    "timestamp": 1700024400000,
    "num_trades": 127658
  },
  "IBM": {
    "symbol": "IBM",
    "name": "International Business Machines Corp",
    "closing_price": 152.58,
    "volume_weighted": 152.4351,
    "open_price": 150.4,
    "high_price": 153.22,
    "low_price": 150.4,
    "timestamp": 1700024400000,
    "num_trades": 71689
  },
  "BA": {
    "symbol": "BA",
    "name": "Boeing Company",
    "closing_price": 208.71,
    "volume_weighted": 209.4476,
    "open_price": 208.21,
    "high_price": 211.09,
    "low_price": 207.6,
    "timestamp": 1700024400000,
    "num_trades": 81024
  },
  "XOM": {
    "symbol": "XOM",
    "name": "Exxon Mobil Corporation",
    "closing_price": 103.66,
    "volume_weighted": 104.1573,
    "open_price": 103.96,
    "high_price": 105.15,
    "low_price": 103.5,
    "timestamp": 1700024400000,
    "num_trades": 175774
  },
  "WMT": {
    "symbol": "WMT",
    "name": "Walmart Inc",
    "closing_price": 169.78,
    "volume_weighted": 169.0908,
    "open_price": 168.38,
    "high_price": 169.94,
    "low_price": 167.51,
    "timestamp": 1700024400000,
    "num_trades": 162635
  },
  "MA": {
    "symbol": "MA",
    "name": "Mastercard Incorporated - Class A",
    "closing_price": 396.83,
    "volume_weighted": 397.4342,
    "open_price": 397.47,
    "high_price": 399.28,
    "low_price": 394.76,
    "timestamp": 1700024400000,
    "num_trades": 47330
  },
  "GS": {
    "symbol": "GS",
    "name": "The Goldman Sachs Group, Inc",
    "closing_price": 337.6,
    "volume_weighted": 337.6547,
    "open_price": 339.9,
    "high_price": 341.08,
    "low_price": 335.3407,
    "timestamp": 1700024400000,
    "num_trades": 40534
  },
  "MRK": {
    "symbol": "MRK",
    "name": "Merck & Co Inc",
    "closing_price": 101.35,
    "volume_weighted": 101.3161,
    "open_price": 101.88,
    "high_price": 102.17,
    "low_price": 100.72,
    "timestamp": 1700024400000,
    "num_trades": 92179
  },
  "CVX": {
    "symbol": "CVX",
    "name": "Chevron Corp",
    "closing_price": 145.56,
    "volume_weighted": 145.686,
    "open_price": 144.86,
    "high_price": 146.64,
    "low_price": 144.41,
    "timestamp": 1700024400000,
    "num_trades": 124422
  },
  "ORCL": {
    "symbol": "ORCL",
    "name": "Oracle Corp",
    "closing_price": 114.06,
    "volume_weighted": 114.6791,
    "open_price": 116.15,
    "high_price": 116.31,
    "low_price": 113.925,
    "timestamp": 1700024400000,
    "num_trades": 80022
  },
  "T": {
    "symbol": "T",
    "name": "AT&T Inc",
    "closing_price": 15.76,
    "volume_weighted": 15.7467,
    "open_price": 15.65,
    "high_price": 15.8,
    "low_price": 15.64,
    "timestamp": 1700024400000,
    "num_trades": 85353
  },
  "KO": {
    "symbol": "KO",
    "name": "Coca-Cola Company",
    "closing_price": 57.21,
    "volume_weighted": 57.0845,
    "open_price": 57.3,
    "high_price": 57.335,
    "low_price": 56.75,
    "timestamp": 1700024400000,
    "num_trades": 116955
  },
  "CMCSA": {
    "symbol": "CMCSA",
    "name": "Comcast Corp",
    "closing_price": 42.53,
    "volume_weighted": 42.4386,
    "open_price": 41.88,
    "high_price": 42.65,
    "low_price": 41.88,
    "timestamp": 1700024400000,
    "num_trades": 96158
  },
  "PM": {
    "symbol": "PM",
    "name": "Philip Morris International Inc",
    "closing_price": 91.73,
    "volume_weighted": 91.1079,
    "open_price": 90.67,
    "high_price": 91.74,
    "low_price": 90.31,
    "timestamp": 1700024400000,
    "num_trades": 56899
  },
  "PEP": {
    "symbol": "PEP",
    "name": "PepsiCo, Inc",
    "closing_price": 167.25,
    "volume_weighted": 167.08,
    "open_price": 168.7,
    "high_price": 168.7889,
    "low_price": 166.27,
    "timestamp": 1700024400000,
    "num_trades": 110935
  },
  "MS": {
    "symbol": "MS",
    "name": "Morgan Stanley",
    "closing_price": 79.68,
    "volume_weighted": 79.5558,
    "open_price": 78.57,
    "high_price": 80.04,
    "low_price": 78.5,
    "timestamp": 1700024400000,
    "num_trades": 98997
  },
  "UPS": {
    "symbol": "UPS",
    "name": "United Parcel Service Inc - Class B",
    "closing_price": 147.17,
    "volume_weighted": 146.7785,
    "open_price": 144,
    "high_price": 147.9,
    "low_price": 143.95,
    "timestamp": 1700024400000,
    "num_trades": 71250
  },
  "MMM": {
    "symbol": "MMM",
    "name": "3M Company",
    "closing_price": 96.82,
    "volume_weighted": 96.7844,
    "open_price": 95.44,
    "high_price": 97.2036,
    "low_price": 95.44,
    "timestamp": 1700024400000,
    "num_trades": 50914
  },
  "WFC": {
    "symbol": "WFC",
    "name": "Wells Fargo & Co.",
    "closing_price": 42.84,
    "volume_weighted": 42.7016,
    "open_price": 42.07,
    "high_price": 43.025,
    "low_price": 42.07,
    "timestamp": 1700024400000,
    "num_trades": 118923
  },
  "CAT": {
    "symbol": "CAT",
    "name": "Caterpillar Inc.",
    "closing_price": 251.09,
    "volume_weighted": 251.1435,
    "open_price": 249.52,
    "high_price": 252.925,
    "low_price": 248.6,
    "timestamp": 1700024400000,
    "num_trades": 65605
  },
  "GE": {
    "symbol": "GE",
    "name": "General Electric Company",
    "closing_price": 116.3,
    "volume_weighted": 116.5119,
    "open_price": 116.96,
    "high_price": 117.5,
    "low_price": 115.723,
    "timestamp": 1700024400000,
    "num_trades": 53680
  },
  "ADBE": {
    "symbol": "ADBE",
    "name": "Adobe Inc.",
    "closing_price": 595.31,
    "volume_weighted": 597.0605,
    "open_price": 605,
    "high_price": 605.73,
    "low_price": 591.79,
    "timestamp": 1700024400000,
    "num_trades": 86132
  },
  "AMGN": {
    "symbol": "AMGN",
    "name": "Amgen Inc.",
    "closing_price": 273.03,
    "volume_weighted": 273.0902,
    "open_price": 270.28,
    "high_price": 274.61,
    "low_price": 270.02,
    "timestamp": 1700024400000,
    "num_trades": 48197
  },
  "TXN": {
    "symbol": "TXN",
    "name": "Texas Instruments Incorporated",
    "closing_price": 151.87,
    "volume_weighted": 151.985,
    "open_price": 151.01,
    "high_price": 153.64,
    "low_price": 150.15,
    "timestamp": 1700024400000,
    "num_trades": 84222
  },
  "MCD": {
    "symbol": "MCD",
    "name": "McDonald's Corporation",
    "closing_price": 270.39,
    "volume_weighted": 270.3999,
    "open_price": 272.43,
    "high_price": 273.1,
    "low_price": 269.025,
    "timestamp": 1700024400000,
    "num_trades": 57551
  },
  "HON": {
    "symbol": "HON",
    "name": "Honeywell International Inc.",
    "closing_price": 189.55,
    "volume_weighted": 189.6737,
    "open_price": 190.48,
    "high_price": 191.76,
    "low_price": 188.78,
    "timestamp": 1700024400000,
    "num_trades": 54317
  },
  "UNH": {
    "symbol": "UNH",
    "name": "UnitedHealth Group Incorporated",
    "closing_price": 538.41,
    "volume_weighted": 537.5858,
    "open_price": 540.05,
    "high_price": 540.46,
    "low_price": 531.7001,
    "timestamp": 1700024400000,
    "num_trades": 67396
  },
  "SPY": {
    "symbol": "SPY",
    "name": "SPDR S&P 500 ETF Trust",
    "closing_price": 449.68,
    "volume_weighted": 450.0195,
    "open_price": 450.11,
    "high_price": 451.38,
    "low_price": 448.8,
    "timestamp": 1700024400000,
    "num_trades": 555373
  },
  "ILMN": {
    "symbol": "ILMN",
    "name": "Illumina Inc.",
    "closing_price": 100.17,
    "volume_weighted": 100.3615,
    "open_price": 98.12,
    "high_price": 102.5,
    "low_price": 97.11,
    "timestamp": 1700024400000,
    "num_trades": 53582
  },
  "GILD": {
    "symbol": "GILD",
    "name": "Gilead Sciences, Inc.",
    "closing_price": 75.04,
    "volume_weighted": 75.0471,
    "open_price": 74.23,
    "high_price": 75.455,
    "low_price": 74.11,
    "timestamp": 1700024400000,
    "num_trades": 70888
  }
}